LICENSE
README.rst
pyproject.toml
setup.py
ray_voxel_overlap/__init__.py
ray_voxel_overlap/_c_overlap_implementation.c
ray_voxel_overlap/_cython_overlap_implementation.c
ray_voxel_overlap/_cython_overlap_implementation.pyx
ray_voxel_overlap/_py_overlap.py
ray_voxel_overlap/_system_matrix.py
ray_voxel_overlap/version.py
ray_voxel_overlap.egg-info/PKG-INFO
ray_voxel_overlap.egg-info/SOURCES.txt
ray_voxel_overlap.egg-info/dependency_links.txt
ray_voxel_overlap.egg-info/requires.txt
ray_voxel_overlap.egg-info/top_level.txt